[
  {
    "type": "ts",
    "directory": "src",
    "output_path": "translations/app/liri-text.ts"
  },
  {
    "type": "desktop",
    "source_file": "data/io.liri.Text.desktop.in",
    "file_filter": "translations/data/io.liri.Text_<lang>.desktop",
    "output_path": "data/io.liri.Text.desktop"
  },
  {
    "type": "metainfo",
    "source_file": "data/io.liri.Text.appdata.xml.in",
    "dest_file": "data/io.liri.Text.appdata.xml",
    "file_filter": "translations/data/metainfo/<lang>.po",
    "output_path": "translations/data/metainfo/metainfo.pot"
  }
]
